ezdatapipe
