Metadata-Version: 1.1
Name: ezdatapipe
Version: 0.0.3
Summary: collection of scripts for structured data processing
Home-page: https://github.com/bzcnsh/ezdatapipe.git
Author: Yimin Zheng
Author-email: bzcnsh@yahoo.com
License: MIT
Keywords: structured data pipeline
Platform: UNKNOWN
Classifier: Development Status :: 3 - Alpha
Classifier: License :: OSI Approved :: MIT License
Classifier: Programming Language :: Python :: 2.7
Classifier: Topic :: Utilities
